pypeertube/__init__.py
pypeertube/channels.py
pypeertube/client.py
pypeertube/exceptions.py
pypeertube/py.typed
pypeertube/validators.py
pypeertube/videos.py
pypeertube-1.0.0.dist-info/licenses/LICENSE
pypeertube-1.0.0.dist-info/METADATA
pypeertube-1.0.0.dist-info/WHEEL
pypeertube-1.0.0.dist-info/top_level.txt
pypeertube-1.0.0.dist-info/RECORD
