Metadata-Version: 2.4
Name: pypeertube
Version: 1.0.0
Summary: Python module to interact with a Peertube instance's API.
Author-email: CaramelConnoisseur <me@caramelconnoisseur.dev>
License-Expression: GPL-3.0-only
Project-URL: Source, https://github.com/CaramelConnoisseur/PyPeertube
Classifier: Development Status :: 5 - Production/Stable
Classifier: Intended Audience :: Developers
Classifier: Natural Language :: English
Classifier: Operating System :: OS Independent
Classifier: Programming Language :: Python :: 3 :: Only
Classifier: Topic :: Multimedia
Classifier: Topic :: Multimedia :: Video
Classifier: Topic :: Multimedia :: Video :: Display
Classifier: Typing :: Typed
Requires-Python: ~=3.9
License-File: LICENSE
Requires-Dist: requests~=2.32.5
Dynamic: license-file
